ibm_sso/__init__.py
ibm_sso/authorize copy.py
ibm_sso/authorize.py
ibm_sso/version.py
ibm_sso/dto/TokenDTO.py
ibm_sso/dto/__init__.py
ibm_sso/util/__init__.py
ibm_sso/util/const.py
ibm_sso/vo/UserInfoVO.py
ibm_sso/vo/__init__.py
ibm_sso-0.3.4.dist-info/LICENSE
ibm_sso-0.3.4.dist-info/METADATA
ibm_sso-0.3.4.dist-info/WHEEL
ibm_sso-0.3.4.dist-info/top_level.txt
ibm_sso-0.3.4.dist-info/RECORD
