Metadata-Version: 2.1
Name: ibm_sso
Version: 0.3.4
Summary: IBM SSO Self-Service Provisioner
Home-page: https://github.com/xiaobitipao/ibm-sso
Author: xiaobitipao
Author-email: xiaobitipao@gmail.com
License: BSD-3-Clause
Keywords: sso,fastapi,oidc
Classifier: Development Status :: 5 - Production/Stable
Classifier: Programming Language :: Python
Classifier: Programming Language :: Python :: 3
Classifier: Programming Language :: Python :: 3.10
Classifier: Programming Language :: Python :: 3.11
Classifier: Programming Language :: Python :: 3.12
Classifier: Programming Language :: Python :: Implementation :: PyPy
Classifier: Intended Audience :: Developers
Classifier: License :: OSI Approved :: BSD License
Classifier: Operating System :: OS Independent
Requires-Python: >=3.10
License-File: LICENSE
Requires-Dist: python-dotenv>=1.0.1
Requires-Dist: fastapi>=0.112.0
Requires-Dist: authlib>=1.3.0
Requires-Dist: requests>=2.32.2
Requires-Dist: httpx>=0.27.0
Requires-Dist: uvicorn>=0.30.0
